tactus/__init__.py
tactus/adapters/__init__.py
tactus/adapters/broker_log.py
tactus/adapters/cli_hitl.py
tactus/adapters/cli_log.py
tactus/adapters/control_loop.py
tactus/adapters/cost_collector_log.py
tactus/adapters/file_storage.py
tactus/adapters/http_callback_log.py
tactus/adapters/ide_log.py
tactus/adapters/lua_tools.py
tactus/adapters/mcp.py
tactus/adapters/mcp_manager.py
tactus/adapters/memory.py
tactus/adapters/plugins.py
tactus/adapters/channels/__init__.py
tactus/adapters/channels/base.py
tactus/adapters/channels/broker.py
tactus/adapters/channels/cli.py
tactus/adapters/channels/host.py
tactus/adapters/channels/ipc.py
tactus/adapters/channels/sse.py
tactus/backends/http_backend.py
tactus/backends/model_backend.py
tactus/backends/pytorch_backend.py
tactus/broker/__init__.py
tactus/broker/client.py
tactus/broker/protocol.py
tactus/broker/server.py
tactus/broker/stdio.py
tactus/cli/__init__.py
tactus/cli/app.py
tactus/cli/control.py
tactus/cli/commands/__init__.py
tactus/core/__init__.py
tactus/core/config_manager.py
tactus/core/dsl_stubs.py
tactus/core/exceptions.py
tactus/core/execution_context.py
tactus/core/lua_sandbox.py
tactus/core/message_history_manager.py
tactus/core/mocking.py
tactus/core/output_validator.py
tactus/core/registry.py
tactus/core/runtime.py
tactus/core/template_resolver.py
tactus/core/yaml_parser.py
tactus/core/dependencies/__init__.py
tactus/core/dependencies/registry.py
tactus/docker/Dockerfile
tactus/docker/Dockerfile.pypi
tactus/docker/entrypoint.sh
tactus/docs/__init__.py
tactus/docs/extractor.py
tactus/docs/html_renderer.py
tactus/docs/models.py
tactus/docs/templates/base.html
tactus/docs/templates/index.html
tactus/docs/templates/module.html
tactus/dspy/__init__.py
tactus/dspy/agent.py
tactus/dspy/broker_lm.py
tactus/dspy/config.py
tactus/dspy/history.py
tactus/dspy/module.py
tactus/dspy/prediction.py
tactus/dspy/signature.py
tactus/formatting/__init__.py
tactus/formatting/formatter.py
tactus/ide/__init__.py
tactus-0.37.0.dist-info/METADATA
tactus-0.37.0.dist-info/WHEEL
tactus-0.37.0.dist-info/entry_points.txt
tactus-0.37.0.dist-info/licenses/LICENSE
tactus-0.37.0.dist-info/RECORD
