Metadata-Version: 2.4
Name: tactus
Version: 0.37.0
Summary: Tactus: Lua-based DSL for agentic workflows
Project-URL: Homepage, https://github.com/AnthusAI/Tactus
Project-URL: Documentation, https://github.com/AnthusAI/Tactus/tree/main/docs
Project-URL: Repository, https://github.com/AnthusAI/Tactus
Project-URL: Issues, https://github.com/AnthusAI/Tactus/issues
Author-email: Anthus <info@anthus.ai>
License: MIT
License-File: LICENSE
Keywords: agents,ai,dsl,llm,lua,workflows
Classifier: Development Status :: 3 - Alpha
Classifier: Intended Audience :: Developers
Classifier: License :: OSI Approved :: MIT License
Classifier: Programming Language :: Python :: 3
Classifier: Programming Language :: Python :: 3.9
Classifier: Programming Language :: Python :: 3.10
Classifier: Programming Language :: Python :: 3.11
Classifier: Programming Language :: Python :: 3.12
Classifier: Topic :: Scientific/Engineering :: Artificial Intelligence
Classifier: Topic :: Software Development :: Libraries :: Python Modules
Requires-Python: >=3.9
Requires-Dist: antlr4-python3-runtime==4.13.1
Requires-Dist: behave>=1.2.6
Requires-Dist: boto3>=1.28.0
Requires-Dist: dotyaml>=0.1.4
Requires-Dist: dspy>=2.5
Requires-Dist: flask-cors>=4.0.0
Requires-Dist: flask>=3.0.0
Requires-Dist: gherkin-official>=28.0.0
Requires-Dist: h5py>=3.10
Requires-Dist: jinja2>=3.0
Requires-Dist: litellm>=1.81.5
Requires-Dist: logfire>=4.20.0
Requires-Dist: lupa>=2.6
Requires-Dist: markdown>=3.0
Requires-Dist: nanoid>=2.0.0
Requires-Dist: nest-asyncio>=1.5.0
Requires-Dist: openpyxl>=3.1
Requires-Dist: opentelemetry-api>=1.39.1
Requires-Dist: opentelemetry-sdk>=1.39.1
Requires-Dist: pyarrow>=14.0
Requires-Dist: pydantic-ai-slim[bedrock,evals]
Requires-Dist: pydantic>=2.0
Requires-Dist: pyyaml
Requires-Dist: rapidfuzz>=3.0.0
Requires-Dist: rich>=13.9.4
Requires-Dist: typer
Provides-Extra: dev
Requires-Dist: antlr4-tools>=0.2.1; extra == 'dev'
Requires-Dist: behave>=1.2.6; extra == 'dev'
Requires-Dist: black==24.10.0; extra == 'dev'
Requires-Dist: coverage>=7.4; extra == 'dev'
Requires-Dist: fastmcp>=2.3.5; (python_version >= '3.10') and extra == 'dev'
Requires-Dist: pytest-asyncio>=0.23; extra == 'dev'
Requires-Dist: pytest-xdist>=3.0; extra == 'dev'
Requires-Dist: pytest>=8.0; extra == 'dev'
Requires-Dist: python-semantic-release>=9.0.0; extra == 'dev'
Requires-Dist: ruff; extra == 'dev'
Provides-Extra: discord
Requires-Dist: discord-py>=2.0; extra == 'discord'
Provides-Extra: email
Requires-Dist: aiosmtplib>=3.0; extra == 'email'
Provides-Extra: notifications
Requires-Dist: aiosmtplib>=3.0; extra == 'notifications'
Requires-Dist: discord-py>=2.0; extra == 'notifications'
Requires-Dist: slack-sdk>=3.0; extra == 'notifications'
Provides-Extra: slack
Requires-Dist: slack-sdk>=3.0; extra == 'slack'
